{"cameraMode":{"drawMode":0,"name":"Shaded","section":"Shading Mode"},"sceneLighting":true,"audioPlay":false,"sceneViewState":{"m_AlwaysRefresh":false,"showFog":true,"showSkybox":true,"showFlares":true,"showImageEffects":true,"showParticleSystems":true,"showVisualEffectGraphs":true,"m_FxEnabled":true},"in2DMode":false,"pivot":{"x":543.9099731445313,"y":10.849065780639649,"z":591.5896606445313},"rotation":{"x":-0.01663648895919323,"y":0.9520016312599182,"z":-0.30108317732810976,"w":-0.052603110671043399},"size":1.5245171785354615,"orthographic":false}